webstor/__init__.py
webstor/_version.py
webstor/webstor.py
webstor/tests/__init__.py
webstor/tests/conftest.py
webstor/tests/test_examples.py
webstor-0.1.19.dist-info/AUTHORS.rst
webstor-0.1.19.dist-info/LICENSE
webstor-0.1.19.dist-info/METADATA
webstor-0.1.19.dist-info/WHEEL
webstor-0.1.19.dist-info/entry_points.txt
webstor-0.1.19.dist-info/top_level.txt
webstor-0.1.19.dist-info/RECORD
