Metadata-Version: 2.1
Name: webstor
Version: 0.1.19
Summary: A script to quickly enumerate all websites across all of your organization's networks, store their responses, and query for known web technologies, such as those with zero-day vulnerabilities.
Home-page: https://github.com/RossGeerlings/webstor
Author: Ross Geerlings
Author-email: 
License: MIT
Platform: UNKNOWN
Classifier: Development Status :: 2 - Pre-Alpha
Classifier: Natural Language :: English
Classifier: Programming Language :: Python :: 3
Requires-Python: >=3.6
License-File: LICENSE
License-File: AUTHORS.rst
Requires-Dist: dnspython
Requires-Dist: beautifulsoup4
Requires-Dist: mysql-connector-python
Requires-Dist: js-regex
Requires-Dist: gevent
Requires-Dist: requests
